odoo/addons/partner_industrial_estate/README.rst
odoo/addons/partner_industrial_estate/__init__.py
odoo/addons/partner_industrial_estate/__manifest__.py
odoo/addons/partner_industrial_estate/hooks.py
odoo/addons/partner_industrial_estate/i18n/es.po
odoo/addons/partner_industrial_estate/models/__init__.py
odoo/addons/partner_industrial_estate/models/res_partner.py
odoo/addons/partner_industrial_estate/models/res_partner_industrial_estate.py
odoo/addons/partner_industrial_estate/readme/CONFIGURE.md
odoo/addons/partner_industrial_estate/readme/CONTRIBUTORS.md
odoo/addons/partner_industrial_estate/readme/DESCRIPTION.md
odoo/addons/partner_industrial_estate/readme/INSTALL.md
odoo/addons/partner_industrial_estate/readme/USAGE.md
odoo/addons/partner_industrial_estate/security/ir.model.access.csv
odoo/addons/partner_industrial_estate/static/description/icon.png
odoo/addons/partner_industrial_estate/static/description/index.html
odoo/addons/partner_industrial_estate/tests/__init__.py
odoo/addons/partner_industrial_estate/tests/test_partner_industrial_estate.py
odoo/addons/partner_industrial_estate/views/res_partner_industrial_estate_views.xml
odoo/addons/partner_industrial_estate/views/res_partner_views.xml
odoo_addon_partner_industrial_estate-18.0.1.0.0.1.dist-info/METADATA
odoo_addon_partner_industrial_estate-18.0.1.0.0.1.dist-info/WHEEL
odoo_addon_partner_industrial_estate-18.0.1.0.0.1.dist-info/top_level.txt
odoo_addon_partner_industrial_estate-18.0.1.0.0.1.dist-info/RECORD
